mycalc/calculator.py
firstMyPac-0.0.1.dist-info/LICENSE
firstMyPac-0.0.1.dist-info/METADATA
firstMyPac-0.0.1.dist-info/WHEEL
firstMyPac-0.0.1.dist-info/top_level.txt
firstMyPac-0.0.1.dist-info/RECORD
