Metadata-Version: 2.1
Name: firstMyPac
Version: 0.0.1
Summary: oss-dev my calculator 0001
Home-page: https://github.com/rhenus9911/calc0001
Download-URL: https://github.com/rhenus9911/calc0001/
Author: jeonghoonbae
Author-email: jeonghoon9911@naver.com
Classifier: Programming Language :: Python :: 3
License-File: LICENSE
